mpllayout/__init__.py
mpllayout/constraints.py
mpllayout/constructions.py
mpllayout/containers.py
mpllayout/geometry.py
mpllayout/layout.py
mpllayout/matplotlibutils.py
mpllayout/primitives.py
mpllayout/solver.py
mpllayout/ui.py
matplotlib_layout-0.1.0.dist-info/LICENCE
matplotlib_layout-0.1.0.dist-info/METADATA
matplotlib_layout-0.1.0.dist-info/WHEEL
matplotlib_layout-0.1.0.dist-info/top_level.txt
matplotlib_layout-0.1.0.dist-info/RECORD
