Metadata-Version: 2.1
Name: matplotlib-layout
Version: 0.1.0
Summary: A package for laying out figures with geometric constraints
Author-email: Jonathan Deng <jonathan.j.deng@gmail.com>
Project-URL: Homepage, https://github.com/jon-deng/mpl-layout
Project-URL: Bug Tracker, https://github.com/jon-deng/mpl-layout/issues
Classifier: Programming Language :: Python :: 3
Classifier: License :: OSI Approved :: MIT License
Classifier: Operating System :: OS Independent
Requires-Python: >=3.7
License-File: LICENCE
